stigg/__init__.py
stigg/_edge_utils.py
stigg/client.py
stigg/generated/__init__.py
stigg/generated/apply_subscription.py
stigg/generated/archive_customer.py
stigg/generated/async_base_client.py
stigg/generated/async_client.py
stigg/generated/base_client.py
stigg/generated/base_model.py
stigg/generated/cancel_subscription.py
stigg/generated/cancel_subscription_updates.py
stigg/generated/client.py
stigg/generated/create_coupon.py
stigg/generated/create_payment_session.py
stigg/generated/create_subscription.py
stigg/generated/delegate_subscription_to_customer.py
stigg/generated/detach_customer_payment_method.py
stigg/generated/enums.py
stigg/generated/estimate_subscription.py
stigg/generated/estimate_subscription_update.py
stigg/generated/exceptions.py
stigg/generated/fragments.py
stigg/generated/get_active_subscriptions.py
stigg/generated/get_active_subscriptions_list.py
stigg/generated/get_automatic_recharge_configuration.py
stigg/generated/get_checkout_state.py
stigg/generated/get_coupons.py
stigg/generated/get_credit_balance.py
stigg/generated/get_credit_grants.py
stigg/generated/get_credit_ledger.py
stigg/generated/get_credit_usage.py
stigg/generated/get_customer_by_id.py
stigg/generated/get_customer_portal_by_ref_id.py
stigg/generated/get_customer_statistics.py
stigg/generated/get_entitlement.py
stigg/generated/get_entitlements.py
stigg/generated/get_entitlements_state.py
stigg/generated/get_mock_paywall.py
stigg/generated/get_paywall.py
stigg/generated/get_products.py
stigg/generated/get_sdk_configuration.py
stigg/generated/get_subscription.py
stigg/generated/get_subscriptions.py
stigg/generated/get_usage_history.py
stigg/generated/get_usage_history_v_2.py
stigg/generated/grant_credits.py
stigg/generated/grant_promotional_entitlements.py
stigg/generated/grant_promotional_entitlements_group.py
stigg/generated/import_customer.py
stigg/generated/import_customer_bulk.py
stigg/generated/import_subscriptions_bulk.py
stigg/generated/input_types.py
stigg_api_client_v2-5.187.0.dist-info/LICENSE
stigg_api_client_v2-5.187.0.dist-info/METADATA
stigg_api_client_v2-5.187.0.dist-info/WHEEL
stigg_api_client_v2-5.187.0.dist-info/RECORD
