Metadata-Version: 2.1
Name: stigg-api-client-v2
Version: 5.187.0
Summary: 
License: STIGG SDK LICENSE
Author: Stigg
Author-email: support@stigg.io
Requires-Python: >=3.9,<4.0
Classifier: License :: Other/Proprietary License
Classifier: Programming Language :: Python :: 3
Classifier: Programming Language :: Python :: 3.9
Classifier: Programming Language :: Python :: 3.10
Classifier: Programming Language :: Python :: 3.11
Requires-Dist: httpx (>=0.23)
Requires-Dist: pydantic (>=2.12,<2.13)
Requires-Dist: tenacity (>=8.2.2,<9.0.0)
